electroket/__init__.py
electroket/pyscf_utils.py
electroket/geometry/cell.py
electroket/hilbert/continuous_hilbert.py
electroket/hilbert/particle.py
electroket/models/__init__.py
electroket/models/gaussian.py
electroket/models/jastrow.py
electroket/models/slater.py
electroket/molecule/__init__.py
electroket/molecule/basis_sto3g.py
electroket/molecule/orbitals.py
electroket/operator/__init__.py
electroket/operator/_continuous_operator.py
electroket/operator/_coulomb.py
electroket/operator/_ewald.py
electroket/operator/_kinetic.py
electroket/operator/_pairinteraction.py
electroket/operator/_potential.py
electroket/operator/_sumoperators.py
electroket/random/__init__.py
electroket/random/particle.py
electroket/sampler/__init__.py
electroket/sampler/rules/__init__.py
electroket/sampler/rules/continuous_gaussian.py
electroket-0.1.0.dist-info/licenses/LICENSE
electroket-0.1.0.dist-info/METADATA
electroket-0.1.0.dist-info/WHEEL
electroket-0.1.0.dist-info/top_level.txt
electroket-0.1.0.dist-info/RECORD
