Metadata-Version: 2.4
Name: electroket
Version: 0.1.0
Summary: A NetKet extension for continuous space problems, with a focus on electronic structure
Author-email: Giuseppe Carleo <name.surname@epfl.ch>
Requires-Python: >=3.8
License-File: LICENSE
Requires-Dist: netket
Provides-Extra: dev
Requires-Dist: pytest; extra == "dev"
Requires-Dist: black; extra == "dev"
Requires-Dist: pyscf; extra == "dev"
Dynamic: license-file
